opoca/__init__.py
opoca/data/README.md
opoca/data/__init__.py
opoca/data/adversarial_validation.py
opoca/data/dataset.py
opoca/data/handler.py
opoca/data/integrations/__init__.py
opoca/data/integrations/salesforce.py
opoca/data/missing_data_handler.py
opoca/data/preprocessing.py
opoca/data/split.py
opoca/data/splitter.py
opoca/data/targets.py
opoca/evaluation/__init__.py
opoca/evaluation/plotter.py
opoca/evaluation/scorer.py
opoca/evaluation/utils.py
opoca/features/__init__.py
opoca/features/pipelines.py
opoca/features/transformers.py
opoca/hyperparam_search/README.MD
opoca/hyperparam_search/__init__.py
opoca/hyperparam_search/examples.py
opoca/hyperparam_search/objective.py
opoca/hyperparam_search/pocstudy.py
opoca/hyperparam_search/utils.py
opoca/models/__init__.py
opoca/models/xgboost_one_vs_rest.py
opoca/quilt_one_time_setup.py
opoca/trainers/__init__.py
opoca/trainers/sklearn.py
opoca-0.1.1.dist-info/LICENSE
opoca-0.1.1.dist-info/WHEEL
opoca-0.1.1.dist-info/METADATA
opoca-0.1.1.dist-info/RECORD
